auth0_component/__init__.py
auth0_component/frontend/dist/index.html
auth0_component/frontend/dist/vite.svg
auth0_component/frontend/dist/assets/index.5223bee9.css
auth0_component/frontend/dist/assets/index.9a5fd6ad.js
streamlit_auth0_component-0.1.5.dist-info/LICENSE
streamlit_auth0_component-0.1.5.dist-info/METADATA
streamlit_auth0_component-0.1.5.dist-info/WHEEL
streamlit_auth0_component-0.1.5.dist-info/top_level.txt
streamlit_auth0_component-0.1.5.dist-info/RECORD
